hyuiauto/__init__.py
hyuiauto/android.py
hyuiauto/ocr.py
hyuiauto/utils.py
hyuiauto/tools/cpu-avx512.exe
hyuiauto/tools/server.py
hyuiauto/tools/android/ADBKeyboard.apk
hyuiauto/tools/android/AdbWinApi.dll
hyuiauto/tools/android/AdbWinUsbApi.dll
hyuiauto/tools/android/adb.exe
hyuiauto/tools/z_dist/androidtool.js
hyuiauto/tools/z_dist/favicon.ico
hyuiauto/tools/z_dist/index.css
hyuiauto/tools/z_dist/index.html
hyuiauto/tools/z_dist/index.js
hyuiauto/tools/z_dist/lib/jquery.min.js
hyuiauto/tools/z_dist/lib/react-dom.production.min.js
hyuiauto/tools/z_dist/lib/react.production.min.js
hyuiauto/tools/z_dist/lib/highlight.js/default.min.css
hyuiauto/tools/z_dist/lib/highlight.js/highlight.min.js
hyuiauto/tools/z_dist/lib/highlight.js/python.min.js
hyuiauto-0.1.6.dist-info/LICENSE.txt
hyuiauto-0.1.6.dist-info/METADATA
hyuiauto-0.1.6.dist-info/WHEEL
hyuiauto-0.1.6.dist-info/top_level.txt
hyuiauto-0.1.6.dist-info/RECORD
